accounts/__init__.py
accounts/admin.py
accounts/apps.py
accounts/backends.py
accounts/forms.py
accounts/models.py
accounts/redirect_path.py
accounts/router.py
accounts/tests.py
accounts/urls.py
accounts/views.py
accounts/migrations/0001_initial.py
accounts/migrations/0002_auto_20211027_0727.py
accounts/migrations/0003_auto_20211028_0404.py
accounts/migrations/0004_user_username.py
accounts/migrations/__init__.py
accounts/templates/account/base.html
accounts/templates/account/email.html
accounts/templates/account/email.txt
accounts/templates/account/login-new.html
accounts/templates/account/login.html
accounts/templates/account/register-new.html
accounts/templates/account/register.html
accounts/templates/account/verification-new.html
cleverange_auth-0.1.10.dist-info/LICENSE
cleverange_auth-0.1.10.dist-info/METADATA
cleverange_auth-0.1.10.dist-info/WHEEL
cleverange_auth-0.1.10.dist-info/top_level.txt
cleverange_auth-0.1.10.dist-info/RECORD
